popex/__init__.py
popex/algorithm.py
popex/cnsts.py
popex/popex_messages.py
popex/popex_objects.py
popex/utils.py
popex/isampl/__init__.py
popex/isampl/neff.py
popex-1.3.1.dist-info/METADATA
popex-1.3.1.dist-info/WHEEL
popex-1.3.1.dist-info/top_level.txt
popex-1.3.1.dist-info/RECORD
