Metadata-Version: 2.1
Name: popex
Version: 1.3.1
Summary: PoPEx sampling package
Home-page: https://github.com/randlab/PoPEx
Author: Christoph Jaeggli
Author-email: christoph.jaeggli@gmail.com
License: MIT
Platform: UNKNOWN
Requires-Dist: numpy
Requires-Dist: scipy
